tesseral_django/__init__.py
tesseral_django/context.py
tesseral_django/credentials.py
tesseral_django/errors.py
tesseral_django/middleware.py
tesseral_django-0.0.3.dist-info/METADATA
tesseral_django-0.0.3.dist-info/WHEEL
tesseral_django-0.0.3.dist-info/RECORD
