Metadata-Version: 2.4
Name: tesseral-django
Version: 0.0.3
Summary: Tesseral SDK for Django
Author-email: Blake Williams <blake.williams@tesseral.com>
Requires-Python: >=3.13
Requires-Dist: django
Requires-Dist: httpx>=0.28.1
Requires-Dist: pytest>=8.4.0
Requires-Dist: tesseral-sdk>=0.0.10
